b24pysdk/__init__.py
b24pysdk/__main__.py
b24pysdk/_config.py
b24pysdk/_constants.py
b24pysdk/_version.py
b24pysdk/client.py
b24pysdk/version.py
b24pysdk/bitrix_api/__init__.py
b24pysdk/bitrix_api/credentials/__init__.py
b24pysdk/bitrix_api/credentials/bitrix_app.py
b24pysdk/bitrix_api/credentials/bitrix_token.py
b24pysdk/bitrix_api/credentials/oauth_event_data.py
b24pysdk/bitrix_api/credentials/oauth_placement_data.py
b24pysdk/bitrix_api/credentials/oauth_token.py
b24pysdk/bitrix_api/credentials/oauth_workflow_data.py
b24pysdk/bitrix_api/credentials/renewed_oauth_token.py
b24pysdk/bitrix_api/credentials/_utils/__init__.py
b24pysdk/bitrix_api/credentials/_utils/parse_flattened_keys.py
b24pysdk/bitrix_api/events/__init__.py
b24pysdk/bitrix_api/events/base_bitrix_event.py
b24pysdk/bitrix_api/events/oauth_token_renewed_event.py
b24pysdk/bitrix_api/events/portal_domain_changed_event.py
b24pysdk/bitrix_api/functions/__init__.py
b24pysdk/bitrix_api/functions/_base_caller.py
b24pysdk/bitrix_api/functions/call.py
b24pysdk/bitrix_api/functions/call_batch.py
b24pysdk/bitrix_api/functions/call_batches.py
b24pysdk/bitrix_api/functions/call_list.py
b24pysdk/bitrix_api/functions/call_list_fast.py
b24pysdk/bitrix_api/functions/call_method.py
b24pysdk/bitrix_api/requesters/__init__.py
b24pysdk/bitrix_api/requesters/_base_requester.py
b24pysdk/bitrix_api/requesters/bitrix_api_requester.py
b24pysdk/bitrix_api/requesters/bitrix_oauth_requester.py
b24pysdk/bitrix_api/requesters/_utils/__init__.py
b24pysdk/bitrix_api/requesters/_utils/parse_response.py
b24pysdk/bitrix_api/requests/__init__.py
b24pysdk/bitrix_api/requests/abstract_bitrix_api_request.py
b24pysdk/bitrix_api/requests/bitrix_api_batch_request.py
b24pysdk/bitrix_api/requests/bitrix_api_list_request.py
b24pysdk/bitrix_api/requests/bitrix_api_request.py
b24pysdk/bitrix_api/requests/bitrix_base_api_request.py
b24pysdk/bitrix_api/responses/__init__.py
b24pysdk/bitrix_api/responses/bitrix_api_batch_response.py
b24pysdk-0.4.0.dist-info/LICENSE
b24pysdk-0.4.0.dist-info/METADATA
b24pysdk-0.4.0.dist-info/WHEEL
b24pysdk-0.4.0.dist-info/top_level.txt
b24pysdk-0.4.0.dist-info/RECORD
