Metadata-Version: 2.1
Name: b24pysdk
Version: 0.4.0
Summary: An official Python library for the Bitrix24 REST API
Author-email: Bitrix24 <pypi@bitrixsoft.com>
License: MIT License
Project-URL: Homepage, https://github.com/bitrix24/b24pysdk
Keywords: bitrix24,rest,api
Requires-Python: >=3.9
License-File: LICENSE
Requires-Dist: psygnal <1.0,>=0.14.1
Requires-Dist: requests <3,>=2.32.4
Requires-Dist: uuid6 <2026.0.0,>=2025.0.0
Provides-Extra: dev
Requires-Dist: pre-commit ; extra == 'dev'
Requires-Dist: ruff ==0.12.1 ; extra == 'dev'
Provides-Extra: test
Requires-Dist: environs >=11.0.0 ; extra == 'test'
Requires-Dist: fastapi[standard] ; extra == 'test'
Requires-Dist: pytest >=7 ; extra == 'test'
Requires-Dist: pytest-cov >=4 ; extra == 'test'
Requires-Dist: pytest-dependency >=0.5.1 ; extra == 'test'
Requires-Dist: pytest-mock >=3 ; extra == 'test'
Requires-Dist: python-multipart ; extra == 'test'
Requires-Dist: uvicorn ; extra == 'test'
